dominion_grpc_proto/__init__.py
dominion_grpc_proto/dominion_pb2.py
dominion_grpc_proto/dominion_pb2_grpc.py
dominion_grpc_proto-0.3.0.dist-info/LICENSE
dominion_grpc_proto-0.3.0.dist-info/METADATA
dominion_grpc_proto-0.3.0.dist-info/WHEEL
dominion_grpc_proto-0.3.0.dist-info/top_level.txt
dominion_grpc_proto-0.3.0.dist-info/RECORD
