Metadata-Version: 2.1
Name: dominion-grpc-proto
Version: 0.3.0
Summary: gRPC protobuf definitions + generated Python code
Home-page: https://github.com/the-gigi/dominion-grpc-proto
Author: Gigi Sayfan
Author-email: the.gigi@gmail.com
License: MIT
Platform: UNKNOWN
Requires-Python: >=3.8
